injected_utils/__init__.py
injected_utils/async_cached_function.py
injected_utils/batched_cache.py
injected_utils/cached_function.py
injected_utils/compressed_cache.py
injected_utils/injected_cache_utils.py
injected_utils/picklability_checker.py
injected_utils/pickling.py
injected_utils/progress.py
injected_utils/shelf_util.py
injected_utils/async_caching/__init__.py
injected_utils/async_caching/async_cache.py
injected_utils/async_caching/async_cached_function.py
injected_utils/async_caching/async_sqlite.py
injected_utils/async_caching/decorators.py
injected_utils-0.1.32.dist-info/METADATA
injected_utils-0.1.32.dist-info/WHEEL
injected_utils-0.1.32.dist-info/RECORD
